[
  {
    "lostItemId": "LI-001",
    "createdAt": "2026-01-22 14:30",
    "plate": "12가3456",
    "zone": "강남역 1번존",
    "itemName": "검정색 장지갑",
    "itemDescription": "조수석 시트 밑에서 발견, 현금 5만원과 신용카드 2장 포함",
    "itemPhotos": [],
    "storageLocation": "본사 분실물 창고 A-1",
    "status": "보관중",
    "handler": "김민준",
    "handedOverAt": "",
    "lostItemCardReceiptNumber": "1234-5678-9012-3456",
    "lostItemCardCompanyName": "신한카드",
    "lostItemCardHolderName": "홍길동"
  },
  {
    "lostItemId": "LI-002",
    "createdAt": "2026-01-22 11:05",
    "plate": "34나7890",
    "zone": "잠실역 2번존",
    "itemName": "에어팟 프로",
    "itemDescription": "뒷좌석 중앙 콘솔에서 발견, 흰색 케이스",
    "itemPhotos": [],
    "storageLocation": "본사 분실물 창고 A-2",
    "status": "보관중",
    "handler": "이서연",
    "handedOverAt": "",
    "lostItemCardReceiptNumber": "",
    "lostItemCardCompanyName": "",
    "lostItemCardHolderName": ""
  },
  {
    "lostItemId": "LI-003",
    "createdAt": "2026-01-21 18:20",
    "plate": "56다1122",
    "zone": "홍대입구 3번존",
    "itemName": "아이패드 에어 4",
    "itemDescription": "조수석 대시보드 위에 놓여 있었음",
    "itemPhotos": [],
    "storageLocation": "본사 분실물 창고 A-3",
    "status": "인계완료",
    "handler": "박지훈",
    "handedOverAt": "2026-01-22 10:00",
    "lostItemCardReceiptNumber": "",
    "lostItemCardCompanyName": "",
    "lostItemCardHolderName": ""
  },
  {
    "lostItemId": "LI-004",
    "createdAt": "2026-01-21 09:45",
    "plate": "78라3344",
    "zone": "판교 1번존",
    "itemName": "차키 (BMW)",
    "itemDescription": "운전석 문 옆 수납공간에서 발견",
    "itemPhotos": [],
    "storageLocation": "판교 지점",
    "status": "보관중",
    "handler": "최수빈",
    "handedOverAt": "",
    "lostItemCardReceiptNumber": "",
    "lostItemCardCompanyName": "",
    "lostItemCardHolderName": ""
  },
  {
    "lostItemId": "LI-005",
    "createdAt": "2026-01-20 20:00",
    "plate": "90마5566",
    "zone": "수원역 2번존",
    "itemName": "선글라스 (레이벤)",
    "itemDescription": "뒷좌석 바닥에서 발견, 약간의 긁힘 있음",
    "itemPhotos": [],
    "storageLocation": "본사 분실물 창고 B-1",
    "status": "폐기",
    "handler": "정다은",
    "handedOverAt": "",
    "lostItemCardReceiptNumber": "",
    "lostItemCardCompanyName": "",
    "lostItemCardHolderName": ""
  },
  {
    "lostItemId": "LI-006",
    "createdAt": "2026-01-20 15:15",
    "plate": "11바7788",
    "zone": "부산역 1번존",
    "itemName": "우산",
    "itemDescription": "트렁크에서 발견, 검정색 3단 우산",
    "itemPhotos": [],
    "storageLocation": "부산 지점",
    "status": "보관중",
    "handler": "강태현",
    "handedOverAt": "",
    "lostItemCardReceiptNumber": "",
    "lostItemCardCompanyName": "",
    "lostItemCardHolderName": ""
  },
  {
    "lostItemId": "LI-007",
    "createdAt": "2026-01-19 12:30",
    "plate": "22사9900",
    "zone": "해운대 2번존",
    "itemName": "신용카드",
    "itemDescription": "운전석 시트 틈새에서 발견",
    "itemPhotos": [],
    "storageLocation": "본사 분실물 창고 A-4",
    "status": "보관중",
    "handler": "윤채원",
    "handedOverAt": "",
    "lostItemCardReceiptNumber": "9876-5432-1098-7654",
    "lostItemCardCompanyName": "국민카드",
    "lostItemCardHolderName": "이영희"
  },
  {
    "lostItemId": "LI-008",
    "createdAt": "2026-01-19 10:00",
    "plate": "33아1212",
    "zone": "대전역 1번존",
    "itemName": "책 (총, 균, 쇠)",
    "itemDescription": "조수석 바닥 매트 위",
    "itemPhotos": [],
    "storageLocation": "대전 지점",
    "status": "인계완료",
    "handler": "임도윤",
    "handedOverAt": "2026-01-20 14:00",
    "lostItemCardReceiptNumber": "",
    "lostItemCardCompanyName": "",
    "lostItemCardHolderName": ""
  },
  {
    "lostItemId": "LI-009",
    "createdAt": "2026-01-18 22:10",
    "plate": "44자3434",
    "zone": "청주 2번존",
    "itemName": "USB 드라이브",
    "itemDescription": "센터 콘솔에서 발견, 32GB, 파란색",
    "itemPhotos": [],
    "storageLocation": "본사 분실물 창고 B-2",
    "status": "보관중",
    "handler": "한유진",
    "handedOverAt": "",
    "lostItemCardReceiptNumber": "",
    "lostItemCardCompanyName": "",
    "lostItemCardHolderName": ""
  },
  {
    "lostItemId": "LI-010",
    "createdAt": "2026-01-18 17:40",
    "plate": "55차5656",
    "zone": "광주 1번존",
    "itemName": "텀블러 (스타벅스)",
    "itemDescription": "뒷좌석 컵홀더에 있었음",
    "itemPhotos": [],
    "storageLocation": "광주 지점",
    "status": "보관중",
    "handler": "서준서",
    "handedOverAt": "",
    "lostItemCardReceiptNumber": "",
    "lostItemCardCompanyName": "",
    "lostItemCardHolderName": ""
  },
  {
    "lostItemId": "LI-011",
    "createdAt": "2026-01-17 13:20",
    "plate": "66카7878",
    "zone": "인천공항 1번존",
    "itemName": "여권",
    "itemDescription": "글로브 박스 안에서 발견",
    "itemPhotos": [],
    "storageLocation": "인천공항 지점",
    "status": "인계완료",
    "handler": "권나은",
    "handedOverAt": "2026-01-18 09:30",
    "lostItemCardReceiptNumber": "",
    "lostItemCardCompanyName": "",
    "lostItemCardHolderName": ""
  },
  {
    "lostItemId": "LI-012",
    "createdAt": "2026-01-17 11:50",
    "plate": "77타9090",
    "zone": "제주공항 1번존",
    "itemName": "목도리",
    "itemDescription": "조수석에 남겨져 있었음, 회색",
    "itemPhotos": [],
    "storageLocation": "제주 지점",
    "status": "보관중",
    "handler": "송하윤",
    "handedOverAt": "",
    "lostItemCardReceiptNumber": "",
    "lostItemCardCompanyName": "",
    "lostItemCardHolderName": ""
  },
  {
    "lostItemId": "LI-013",
    "createdAt": "2026-01-16 19:00",
    "plate": "12가3456",
    "zone": "강남역 1번존",
    "itemName": "서류 봉투",
    "itemDescription": "뒷좌석에서 발견, 노란색 봉투, 회사 서류로 추정",
    "itemPhotos": [],
    "storageLocation": "본사 분실물 창고 A-5",
    "status": "보관중",
    "handler": "김민준",
    "handedOverAt": "",
    "lostItemCardReceiptNumber": "",
    "lostItemCardCompanyName": "",
    "lostItemCardHolderName": ""
  },
  {
    "lostItemId": "LI-014",
    "createdAt": "2026-01-16 16:30",
    "plate": "34나7890",
    "zone": "잠실역 2번존",
    "itemName": "핸드폰 충전기",
    "itemDescription": "USB-C 타입, 시거잭에 꽂혀 있었음",
    "itemPhotos": [],
    "storageLocation": "본사 분실물 창고 C-1",
    "status": "폐기",
    "handler": "이서연",
    "handedOverAt": "",
    "lostItemCardReceiptNumber": "",
    "lostItemCardCompanyName": "",
    "lostItemCardHolderName": ""
  },
  {
    "lostItemId": "LI-015",
    "createdAt": "2026-01-15 14:00",
    "plate": "90마5566",
    "zone": "수원역 2번존",
    "itemName": "장갑",
    "itemDescription": "운전석 바닥에서 한 짝 발견, 검정 가죽 장갑",
    "itemPhotos": [],
    "storageLocation": "본사 분실물 창고 B-3",
    "status": "보관중",
    "handler": "정다은",
    "handedOverAt": "",
    "lostItemCardReceiptNumber": "",
    "lostItemCardCompanyName": "",
    "lostItemCardHolderName": ""
  },
  {
    "lostItemId": "LI-016",
    "createdAt": "2026-01-15 10:10",
    "plate": "78라3344",
    "zone": "판교 1번존",
    "itemName": "법인카드",
    "itemDescription": "센터페시아 하단 수납함에서 발견",
    "itemPhotos": [],
    "storageLocation": "본사 분실물 창고 A-6",
    "status": "인계완료",
    "handler": "최수빈",
    "handedOverAt": "2026-01-16 11:00",
    "lostItemCardReceiptNumber": "1122-3344-5566-7788",
    "lostItemCardCompanyName": "삼성카드",
    "lostItemCardHolderName": "(주)테스트"
  },
  {
    "lostItemId": "LI-017",
    "createdAt": "2026-01-14 21:20",
    "plate": "11바7788",
    "zone": "부산역 1번존",
    "itemName": "운동화",
    "itemDescription": "트렁크 안에서 발견, 나이키, 270mm",
    "itemPhotos": [],
    "storageLocation": "부산 지점",
    "status": "보관중",
    "handler": "강태현",
    "handedOverAt": "",
    "lostItemCardReceiptNumber": "",
    "lostItemCardCompanyName": "",
    "lostItemCardHolderName": ""
  },
  {
    "lostItemId": "LI-018",
    "createdAt": "2026-01-14 13:00",
    "plate": "56다1122",
    "zone": "홍대입구 3번존",
    "itemName": "안경",
    "itemDescription": "조수석 의자 위에서 발견, 검은 뿔테",
    "itemPhotos": [],
    "storageLocation": "본사 분실물 창고 B-4",
    "status": "보관중",
    "handler": "박지훈",
    "handedOverAt": "",
    "lostItemCardReceiptNumber": "",
    "lostItemCardCompanyName": "",
    "lostItemCardHolderName": ""
  },
  {
    "lostItemId": "LI-019",
    "createdAt": "2026-01-13 18:50",
    "plate": "33아1212",
    "zone": "대전역 1번존",
    "itemName": "블루투스 스피커",
    "itemDescription": "뒷좌석 선반에서 발견, JBL Go 3",
    "itemPhotos": [],
    "storageLocation": "대전 지점",
    "status": "보관중",
    "handler": "임도윤",
    "handedOverAt": "",
    "lostItemCardReceiptNumber": "",
    "lostItemCardCompanyName": "",
    "lostItemCardHolderName": ""
  },
  {
    "lostItemId": "LI-020",
    "createdAt": "2026-01-13 09:00",
    "plate": "22사9900",
    "zone": "해운대 2번존",
    "itemName": "모자",
    "itemDescription": "뒷좌석에서 발견, 흰색 야구모자",
    "itemPhotos": [],
    "storageLocation": "부산 지점",
    "status": "폐기",
    "handler": "윤채원",
    "handedOverAt": "",
    "lostItemCardReceiptNumber": "",
    "lostItemCardCompanyName": "",
    "lostItemCardHolderName": ""
  },
  {
    "lostItemId": "LI-021",
    "createdAt": "2026-01-22 09:15",
    "plate": "88호1111",
    "zone": "강남역 2번존",
    "itemName": "노트북 파우치",
    "itemDescription": "뒷좌석 바닥에서 발견, 회색, 15인치용",
    "itemPhotos": [],
    "storageLocation": "본사 분실물 창고 C-2",
    "status": "보관중",
    "handler": "김민준",
    "handedOverAt": "",
    "lostItemCardReceiptNumber": "",
    "lostItemCardCompanyName": "",
    "lostItemCardHolderName": ""
  },
  {
    "lostItemId": "LI-022",
    "createdAt": "2026-01-21 17:30",
    "plate": "99보2222",
    "zone": "역삼역 5번존",
    "itemName": "마우스 (로지텍)",
    "itemDescription": "조수석 시트 아래에서 발견, 무선 마우스",
    "itemPhotos": [],
    "storageLocation": "본사 분실물 창고 C-3",
    "status": "보관중",
    "handler": "이서연",
    "handedOverAt": "",
    "lostItemCardReceiptNumber": "",
    "lostItemCardCompanyName": "",
    "lostItemCardHolderName": ""
  },
  {
    "lostItemId": "LI-023",
    "createdAt": "2026-01-21 14:00",
    "plate": "11가3333",
    "zone": "코엑스 주차장",
    "itemName": "회사 출입증",
    "itemDescription": "운전석 대시보드 위에 있었음, 목걸이 형태",
    "itemPhotos": [],
    "storageLocation": "본사 분실물 창고 A-7",
    "status": "인계완료",
    "handler": "박지훈",
    "handedOverAt": "2026-01-22 11:00",
    "lostItemCardReceiptNumber": "",
    "lostItemCardCompanyName": "",
    "lostItemCardHolderName": ""
  },
  {
    "lostItemId": "LI-024",
    "createdAt": "2026-01-20 19:20",
    "plate": "22나4444",
    "zone": "성수역 3번존",
    "itemName": "립밤",
    "itemDescription": "센터콘솔 컵홀더에서 발견, 유리아쥬 제품",
    "itemPhotos": [],
    "storageLocation": "본사 분실물 창고 D-1",
    "status": "폐기",
    "handler": "최수빈",
    "handedOverAt": "",
    "lostItemCardReceiptNumber": "",
    "lostItemCardCompanyName": "",
    "lostItemCardHolderName": ""
  },
  {
    "lostItemId": "LI-025",
    "createdAt": "2026-01-20 11:45",
    "plate": "33다5555",
    "zone": "을지로입구역",
    "itemName": "보조배터리",
    "itemDescription": "글로브 박스에서 발견, 검은색, 샤오미 제품",
    "itemPhotos": [],
    "storageLocation": "본사 분실물 창고 C-4",
    "status": "보관중",
    "handler": "정다은",
    "handedOverAt": "",
    "lostItemCardReceiptNumber": "",
    "lostItemCardCompanyName": "",
    "lostItemCardHolderName": ""
  },
  {
    "lostItemId": "LI-026",
    "createdAt": "2026-01-19 20:50",
    "plate": "44라6666",
    "zone": "동대문역사문화공원",
    "itemName": "문화상품권",
    "itemDescription": "조수석 햇빛 가리개에서 발견, 1만원권 2장",
    "itemPhotos": [],
    "storageLocation": "본사 분실물 창고 A-8",
    "status": "보관중",
    "handler": "강태현",
    "handedOverAt": "",
    "lostItemCardReceiptNumber": "",
    "lostItemCardCompanyName": "",
    "lostItemCardHolderName": ""
  },
  {
    "lostItemId": "LI-027",
    "createdAt": "2026-01-19 15:00",
    "plate": "55마7777",
    "zone": "서울역 3번존",
    "itemName": "다이어리",
    "itemDescription": "뒷좌석 시트 위에 있었음, 갈색 가죽 커버",
    "itemPhotos": [],
    "storageLocation": "본사 분실물 창고 B-5",
    "status": "인계완료",
    "handler": "윤채원",
    "handedOverAt": "2026-01-20 16:30",
    "lostItemCardReceiptNumber": "",
    "lostItemCardCompanyName": "",
    "lostItemCardHolderName": ""
  },
  {
    "lostItemId": "LI-028",
    "createdAt": "2026-01-18 16:10",
    "plate": "66바8888",
    "zone": "용산역 아이파크몰",
    "itemName": "향수",
    "itemDescription": "조수석 문 수납칸에서 발견, 조말론, 라임 바질 만다린",
    "itemPhotos": [],
    "storageLocation": "본사 분실물 창고 B-6",
    "status": "보관중",
    "handler": "임도윤",
    "handedOverAt": "",
    "lostItemCardReceiptNumber": "",
    "lostItemCardCompanyName": "",
    "lostItemCardHolderName": ""
  },
  {
    "lostItemId": "LI-029",
    "createdAt": "2026-01-18 11:25",
    "plate": "77사9999",
    "zone": "고속터미널 경부선",
    "itemName": "책 (여행의 이유)",
    "itemDescription": "뒷좌석 바닥에서 발견",
    "itemPhotos": [],
    "storageLocation": "본사 분실물 창고 D-2",
    "status": "보관중",
    "handler": "한유진",
    "handedOverAt": "",
    "lostItemCardReceiptNumber": "",
    "lostItemCardCompanyName": "",
    "lostItemCardHolderName": ""
  },
  {
    "lostItemId": "LI-030",
    "createdAt": "2026-01-17 22:00",
    "plate": "88아0000",
    "zone": "사당역 4번출구",
    "itemName": "만년필",
    "itemDescription": "센터콘솔에서 발견, 라미 사파리, 검정색",
    "itemPhotos": [],
    "storageLocation": "본사 분실물 창고 A-9",
    "status": "보관중",
    "handler": "서준서",
    "handedOverAt": "",
    "lostItemCardReceiptNumber": "",
    "lostItemCardCompanyName": "",
    "lostItemCardHolderName": ""
  },
  {
    "lostItemId": "LI-031",
    "createdAt": "2026-01-17 18:30",
    "plate": "12가3456",
    "zone": "강남역 1번존",
    "itemName": "블루투스 이어폰 (케이스 없음)",
    "itemDescription": "운전석 시트와 콘솔 사이 틈에서 발견, 왼쪽 유닛",
    "itemPhotos": [],
    "storageLocation": "본사 분실물 창고 C-5",
    "status": "보관중",
    "handler": "권나은",
    "handedOverAt": "",
    "lostItemCardReceiptNumber": "",
    "lostItemCardCompanyName": "",
    "lostItemCardHolderName": ""
  },
  {
    "lostItemId": "LI-032",
    "createdAt": "2026-01-16 20:00",
    "plate": "34나7890",
    "zone": "잠실역 2번존",
    "itemName": "야구공",
    "itemDescription": "트렁크에서 발견, 싸인볼",
    "itemPhotos": [],
    "storageLocation": "본사 분실물 창고 D-3",
    "status": "인계완료",
    "handler": "송하윤",
    "handedOverAt": "2026-01-17 15:00",
    "lostItemCardReceiptNumber": "",
    "lostItemCardCompanyName": "",
    "lostItemCardHolderName": ""
  },
  {
    "lostItemId": "LI-033",
    "createdAt": "2026-01-16 12:10",
    "plate": "99보2222",
    "zone": "역삼역 5번존",
    "itemName": "외장하드",
    "itemDescription": "조수석 글로브박스에서 발견, WD, 1TB, 검정색",
    "itemPhotos": [],
    "storageLocation": "본사 분실물 창고 B-7",
    "status": "보관중",
    "handler": "김민준",
    "handedOverAt": "",
    "lostItemCardReceiptNumber": "",
    "lostItemCardCompanyName": "",
    "lostItemCardHolderName": ""
  },
  {
    "lostItemId": "LI-034",
    "createdAt": "2026-01-15 17:50",
    "plate": "11가3333",
    "zone": "코엑스 주차장",
    "itemName": "손소독제",
    "itemDescription": "운전석 문 수납칸에서 발견, 겔 타입",
    "itemPhotos": [],
    "storageLocation": "본사 분실물 창고 D-4",
    "status": "폐기",
    "handler": "이서연",
    "handedOverAt": "",
    "lostItemCardReceiptNumber": "",
    "lostItemCardCompanyName": "",
    "lostItemCardHolderName": ""
  },
  {
    "lostItemId": "LI-035",
    "createdAt": "2026-01-15 11:30",
    "plate": "44라6666",
    "zone": "동대문역사문화공원",
    "itemName": "귀걸이",
    "itemDescription": "조수석 바닥 매트에서 발견, 은색 링 귀걸이 한쪽",
    "itemPhotos": [],
    "storageLocation": "본사 분실물 창고 A-10",
    "status": "보관중",
    "handler": "박지훈",
    "handedOverAt": "",
    "lostItemCardReceiptNumber": "",
    "lostItemCardCompanyName": "",
    "lostItemCardHolderName": ""
  },
  {
    "lostItemId": "LI-036",
    "createdAt": "2026-01-14 16:00",
    "plate": "66바8888",
    "zone": "용산역 아이파크몰",
    "itemName": "영화티켓",
    "itemDescription": "센터콘솔 컵홀더에서 발견, CGV, 2매",
    "itemPhotos": [],
    "storageLocation": "본사 분실물 창고 D-5",
    "status": "폐기",
    "handler": "최수빈",
    "handedOverAt": "",
    "lostItemCardReceiptNumber": "",
    "lostItemCardCompanyName": "",
    "lostItemCardHolderName": ""
  },
  {
    "lostItemId": "LI-037",
    "createdAt": "2026-01-14 09:40",
    "plate": "88아0000",
    "zone": "사당역 4번출구",
    "itemName": "차량용 충전기 케이블",
    "itemDescription": "뒷좌석 바닥에서 발견, 아이폰용 라이트닝 케이블",
    "itemPhotos": [],
    "storageLocation": "본사 분실물 창고 C-6",
    "status": "보관중",
    "handler": "정다은",
    "handedOverAt": "",
    "lostItemCardReceiptNumber": "",
    "lostItemCardCompanyName": "",
    "lostItemCardHolderName": ""
  },
  {
    "lostItemId": "LI-038",
    "createdAt": "2026-01-13 14:20",
    "plate": "12가3456",
    "zone": "강남역 1번존",
    "itemName": "명함지갑",
    "itemDescription": "운전석 햇빛 가리개에서 발견, 갈색 가죽",
    "itemPhotos": [],
    "storageLocation": "본사 분실물 창고 B-8",
    "status": "인계완료",
    "handler": "강태현",
    "handedOverAt": "2026-01-14 10:00",
    "lostItemCardReceiptNumber": "",
    "lostItemCardCompanyName": "",
    "lostItemCardHolderName": ""
  },
  {
    "lostItemId": "LI-039",
    "createdAt": "2026-01-12 19:00",
    "plate": "99보2222",
    "zone": "역삼역 5번존",
    "itemName": "물티슈",
    "itemDescription": "뒷좌석 문 수납칸에서 발견, 미개봉",
    "itemPhotos": [],
    "storageLocation": "본사 분실물 창고 D-6",
    "status": "보관중",
    "handler": "윤채원",
    "handedOverAt": "",
    "lostItemCardReceiptNumber": "",
    "lostItemCardCompanyName": "",
    "lostItemCardHolderName": ""
  },
  {
    "lostItemId": "LI-040",
    "createdAt": "2026-01-12 15:30",
    "plate": "11가3333",
    "zone": "코엑스 주차장",
    "itemName": "필통",
    "itemDescription": "조수석 시트 밑에서 발견, 캐릭터 필통",
    "itemPhotos": [],
    "storageLocation": "본사 분실물 창고 C-7",
    "status": "보관중",
    "handler": "임도윤",
    "handedOverAt": "",
    "lostItemCardReceiptNumber": "",
    "lostItemCardCompanyName": "",
    "lostItemCardHolderName": ""
  }
]